gsrest/__init__.py
gsrest/cli.py
gsrest/client.py
gsrest/collection.py
gsrest/core/__init__.py
gsrest/core/connect.py
gsrest/core/element.py
gsrest/core/registry.py
gsrest/core/schema.py
gsrest/core/traits.py
gsrest/core/url.py
gsrest/elements/__init__.py
gsrest/elements/blobstore.py
gsrest/elements/coverage.py
gsrest/elements/coveragestore.py
gsrest/elements/gridset.py
gsrest/elements/gwclayer.py
gsrest/elements/layer.py
gsrest/elements/layergroup.py
gsrest/elements/style.py
gsrest/elements/workspace.py
gsrest/helper/__init__.py
gsrest/helper/decorator.py
gsrest/helper/function.py
gsrest/helper/types.py
gsrest/ops.py
gsrest/xml/__init__.py
gsrest/xml/converter.py
gsrest/xml/io.py
gsrest/xml/schema.py
gsrest/yaml.py
gsrest-0.2.1.dist-info/entry_points.txt
gsrest-0.2.1.dist-info/LICENSE
gsrest-0.2.1.dist-info/WHEEL
gsrest-0.2.1.dist-info/METADATA
gsrest-0.2.1.dist-info/RECORD
