Metadata-Version: 2.1
Name: gsrest
Version: 0.2.1
Summary: GeoServer python REST API client
Home-page: https://github.com/esuarezsantana/gsrest
License: GPL-3.0-or-later
Keywords: geoserver,gis,client,rest
Author: Eduardo Suarez-Santana
Requires-Python: >=3.7,<4.0
Classifier: Development Status :: 3 - Alpha
Classifier: License :: OSI Approved :: GNU General Public License v3 or later (GPLv3+)
Classifier: Programming Language :: Python :: 3
Classifier: Programming Language :: Python :: 3.7
Classifier: Programming Language :: Python :: 3.8
Classifier: Topic :: Scientific/Engineering :: GIS
Requires-Dist: pyyaml (>=5.3.1,<6.0.0)
Project-URL: Repository, https://github.com/esuarezsantana/gsrest
